torrent_ds/__init__.py
torrent_ds/config.py
torrent_ds/creds.py
torrent_ds/data.py
torrent_ds/download.py
torrent_ds/error.py
torrent_ds/logger.py
torrent_ds/torrent_ds.py
torrent_ds/util.py
torrent_ds_tools/read_data.py
torrent_ds-2.0.4.dist-info/entry_points.txt
torrent_ds-2.0.4.dist-info/LICENSE
torrent_ds-2.0.4.dist-info/WHEEL
torrent_ds-2.0.4.dist-info/METADATA
torrent_ds-2.0.4.dist-info/RECORD
