Metadata-Version: 2.1
Name: torrent-ds
Version: 2.0.4
Summary: Manage downloads using ncoreparser package.
Home-page: https://github.com/radaron/torrent-ds
License: MIT
Author: Aron Radics
Author-email: aron.radics.jozsef@gmail.com
Requires-Python: >=3.8,<4.0
Classifier: License :: OSI Approved :: MIT License
Classifier: Programming Language :: Python :: 3
Classifier: Programming Language :: Python :: 3.8
Classifier: Programming Language :: Python :: 3.9
Classifier: Programming Language :: Python :: 3.10
Requires-Dist: cryptography (==3.3.2)
Requires-Dist: ncoreparser
Requires-Dist: pyopenssl (==19.1.0)
Requires-Dist: sqlalchemy (==1.3.16)
Requires-Dist: transmissionrpc-ng (==0.12.0)
